[{"chunk_id": "vision_all_gtp_25_1329_bd385e47_p0000", "paper_id": "gtp_25_1329_bd385e47", "title": "gtp-25-1329", "section": "Visual/Equation Content - Page 1", "text": "[VISUAL/EQUATION CONTENT - Page 1]\nHere's the extracted technical content from the provided image:\n\n**1. Mathematical Equations:**\n\nNO_VISUAL_CONTENT\n\n**2. Graphs/Charts:**\n\nNO_VISUAL_CONTENT\n\n**3. Tables:**\n\nNO_VISUAL_CONTENT\n\n**4. Diagrams:**\n\nNO_VISUAL_CONTENT\n\n**5. Key Numbers, Constants, Parameters:**\n\n*   DOI: 10.1115/1.4069776\n*   NOx emissions (referencing source [1])\n*   CO2 concentrations (referencing source [2])\n*   EGR implementation referencing [3,4]\n*   Volume: Vol. 148\n*   Article number: 041018-1", "chunk_type": "vision", "page": 1, "extraction": "gemini_flash_smart"}, {"chunk_id": "vision_all_gtp_25_1329_bd385e47_p0002", "paper_id": "gtp_25_1329_bd385e47", "title": "gtp-25-1329", "section": "Visual/Equation Content - Page 3", "text": "[VISUAL/EQUATION CONTENT - Page 3]\nHere's the technical content extracted from the image:\n\n**1. Mathematical Equations:**\n\n*   Yo2 = 16.6%\n\n**2. Graphs/Charts**\n\n*   NO_VISUAL_CONTENT\n\n**3. Tables**\n\n*   Table 1 (mentioned):  Summarizing seven different configurations.\n\n**4. Diagrams:**\n\n*   **Fig. 1 (a) Combustion test cell plant:**\n    *   H2 Generator\n    *   Flow meters\n    *   H2 line\n    *   Filter\n    *   Natural gas compressor\n    *   Filters\n    *   DRIER\n    *   Air Tank\n    *   CO2 Tank\n    *   Orifice Flowmeter\n    *   HEATER\n    *   Rig\n    *   Exhaust\n    *   Duct\n    *   Stack\n    *   water line\n    *   water cooling line\n    *   NG Pilot line\n    *   NG Premix line\n\n*   **Fig. 1 (b) Reactive test rig:**\n    *   Two perpendicular optical accesses\n    *   Emission probe\n    *   Waterjacket\n    *   Spark plug\n    *   Camera position\n\n*   **Fig. 2 (a) Cross section of the reactive test rig:**\n    *   Burner\n    *   Preheated air\n    *   Effusion cooled dome\n    *   Window\n    *   Emission probe\n    *   Fuel\n    *   Camera Fov\n    *   Exhaust Gases\n    *   Quartz cylindrical liner\n    *   Vessel upstream\n    *   Vessel downstream\n    *   PCB sensor\n\n*   **Fig. 2 (b) Investigated burner schematic:**\n    *   Outer swirler\n    *   Inner swirler\n    *   OX (oxidizer)\n    *   PMX (premix line)\n    *   PLT (pilot line)\n    *   CB (center-body line)\n    *   Center-body\n    *   Converging duct\n\n**5. Key Numbers, Constants, Parameters:**\n\n*   TP TOT - Total thermal power\n*   TP REF - Reference value\n*   Yo2 - Inlet oxygen mass fraction", "chunk_type": "vision", "page": 3, "extraction": "gemini_flash_smart"}, {"chunk_id": "vision_all_gtp_25_1329_bd385e47_p0003", "paper_id": "gtp_25_1329_bd385e47", "title": "gtp-25-1329", "section": "Visual/Equation Content - Page 4", "text": "[VISUAL/EQUATION CONTENT - Page 4]\nHere's the technical content extracted from the provided text.\n\n**1. Mathematical Equations**\n\nNO_VISUAL_CONTENT\n\n**2. Graphs/Charts**\n\nNO_VISUAL_CONTENT\n\n**3. Tables**\n\n**Table 1: Investigated burner configurations**\n\n| N (-) | D (mm) | Direction | \u03a6 (deg) | Position | CB |\n|---|---|---|---|---|---|\n| B0 | N | D | Outward | \u03a6REF | Inner swirler | - |\n| B1 | N | 1.2D | Outward, Swirled | \u03a6REF | Outer swirler | - |\n| B2 | 2N | 0.7D | Outward | \u03a6REF | Outer swirler | - |\n| B4 | N | 0.7D | Straight | 0 | Outer swirler | - |\n| B5-PMX | N | D | Outward | \u03a6REF | Outer swirler | - |\n| B5-CB | N | D | Outward | \u03a6REF | Outer swirler | YES |\n| B6 | N | D | 2 x Outward | 2\u03a6REF | Outer swirler | - |\n\n**Table 2: Tested operating conditions**\n\n| Parameter | Value | Unit |\n|---|---|---|\n| Tinlet | 300 | (\u00b0C) |\n| \u0394P/P | 4.2 | (%) |\n| TPtot | TPREF | (kW) |\n| PMX% | 0~95 | (%) |\n| TP(H\u2082) % | 0-5-10 | (%) |\n| YO2 | 23.2-16.6 | (%mass) |\n\n**4. Diagrams**\n\nNO_VISUAL_CONTENT\n\n**5. Key Numbers, Constants, Parameters**\n\n*   Hydrogen fraction maintained below 10% of total thermal power.\n*   Inlet temperature of oxidizer: Tinlet = 300\u00b0C.\n*  \u0394P/P = 4.2%\n*   PMX% = 0~95%\n*   TP(H2)% = 0~5-10%\n*   YO2 = 23.2~16.6 %mass", "chunk_type": "vision", "page": 4, "extraction": "gemini_flash_smart"}, {"chunk_id": "vision_all_gtp_25_1329_bd385e47_p0004", "paper_id": "gtp_25_1329_bd385e47", "title": "gtp-25-1329", "section": "Visual/Equation Content - Page 5", "text": "[VISUAL/EQUATION CONTENT - Page 5]\nHere's a breakdown of the technical information extracted from the image:\n\n**1. Mathematical Equations:**\nNO_VISUAL_CONTENT\n\n**2. Graphs/Charts:**\nThe image contains 18 heatmaps.\n*   **Axes:**\n    *   x-axis: x (mm), ranges from 0 to 125\n    *   y-axis: y (mm), ranges from -50 to 50\n*   **Units:** mm for x and y axis\n*   **Curves:** Heatmaps showing normalized OH* chemiluminescence intensity.\n*   **Key Values:**\n    *   Colorbar: Normalized OH intensity, ranging from 0 to 1, representing OH*/OH*MAX.\n\n**3. Tables:**\nNO_VISUAL_CONTENT\n\n**4. Diagrams:**\nThe images depict the burner. There are 6 sections depending on the burner geometry: B0, B1, B2, B4, B5PMX, B5CB, B6. The names are labeled on top of the charts.\n\n**5. Key Numbers, Constants, Parameters:**\n\n*0%PMX-TP(H2)= 0% - Air\n*50%PMX-TP(H2)= 5% - Air\n*50%PMX-TP(H2)= 5% - EGR", "chunk_type": "vision", "page": 5, "extraction": "gemini_flash_smart"}, {"chunk_id": "vision_all_gtp_25_1329_bd385e47_p0005", "paper_id": "gtp_25_1329_bd385e47", "title": "gtp-25-1329", "section": "Visual/Equation Content - Page 6", "text": "[VISUAL/EQUATION CONTENT - Page 6]\nHere's a breakdown of the technical content extracted from the provided text and figures:\n\n**1. Mathematical Equations:**\n\n*  TP(H2) = 5%\n\n**2. Graphs/Charts:**\n\n*   **Fig. 4: LBO limits for different burner configurations with 100%NG and standard air as oxidizer**\n    *   Axes:\n        *   Y-axis: LBO / LBO(REF)\n        *   X-axis: Burner Configuration (B0, B1, B2, B4, B5-CB, B5-PMX, B6)\n    *   Curves:\n        *   50% PMX (Blue bars)\n        *   70% PMX (Red bars)\n        *   Baseline (dashed black line - approximate value ~ 0.66 on Y axis)\n\n*   **Fig. 5: Temperature measured on the dome cold side for 100%NG and TPREF**\n    *   Axes:\n        *   Y-axis: Tdome cold - TREF (\u00b0C)\n        *   X-axis: PMX (%)\n    *   Curves:\n        *   B0 (Blue circles)\n        *   B1 (Orange triangles)\n        *   B2 (Green inverted triangles)\n        *   B4 (Purple diamonds)\n        *   B5-PMX (Olive Green right-pointing triangles)\n        *   B5-CB (Teal left-pointing triangles)\n        *   B6 (Red squares)\n\n*   **Fig. 6: Premix fraction stably achievable for different burner configurations with standard air as oxidizer**\n    *   Axes:\n        *   Y-axis: PMXcr (%)\n        *   X-axis: Burner Configuration (B0, B1, B2, B4, B5-PMX, B6)\n    *   Curves:\n        *   100% NG (Blue bars)\n        *   PLT(H2) (Orange bars)\n        *   Baseline (dashed black line, approximate value around 80% on the Y axis)\n\n**3. Tables:**\nNO_VISUAL_CONTENT\n\n**4. Diagrams:**\n*   Small diagram above Fig. 5:\n    *   Components: \"Burner outlet\", \"TC\" (Thermocouple)\n\n**5. Key Numbers, Constants, Parameters:**\n\n*   50% PMX\n*   70% PMX\n*   100% NG\n*   LBO (Lean Blowout)\n*   TREF\n*   PMX (%) - Premix fraction in percentage\n*   PMXcr (%) - Premix fraction stably achievable in percentage", "chunk_type": "vision", "page": 6, "extraction": "gemini_flash_smart"}, {"chunk_id": "vision_all_gtp_25_1329_bd385e47_p0006", "paper_id": "gtp_25_1329_bd385e47", "title": "gtp-25-1329", "section": "Visual/Equation Content - Page 7", "text": "[VISUAL/EQUATION CONTENT - Page 7]\nHere's the extracted technical content from the gas turbine research page:\n\n**1. Mathematical Equations:**\n\n*   TP(H2) = TPPLT (Total thermal power with Hydrogen = Total thermal power with Pilot Line)\n\n**2. Graphs/Charts:**\n\n*   **Fig. 7(a) CO with 100%NG:**\n    *   Axes:\n        *   X-axis: PMX (%), Premix Fraction\n        *   Y-axis: CO (ppm), Carbon Monoxide Concentration\n    *   Curves:\n        *   B0: Triangle curve\n        *   B1: Plus curve\n        *   B2: Inverted Triangle curve\n        *   B4: Diamond curve\n        *   B5-PMX: Star curve\n        *   B5-CB: Asterisk curve\n        *   B6: Square curve\n    *   Key Values:\n        *   PMX: 0 - 100%\n        *   CO goes from 20 to 70 around 0  PMX\n        *   CO ranges from 0-100.\n\n*   **Fig. 7(b) NOx with 100%NG:**\n    *   Axes:\n        *   X-axis: PMX (%), Premix Fraction\n        *   Y-axis: NOx (ppm), Nitrogen Oxides Concentration\n    *   Curves:\n        *   B0: Triangle Curve\n        *   B1: Plus Curve\n        *   B2: Inverted Triangle Curve\n        *   B4: Diamond Curve\n        *   B5-PMX: Star Curve\n        *   B5-CB: Asterisk Curve\n        *   B6: Square Curve\n    *   Key Values:\n        *   PMX: 0 - 100%\n        *   NOx goes from 50(B6) to 60(B0) around 0 PMX.\n        *   NOx ranges from 0 to 70.\n\n*   **Fig. 8 B2 Transient:**\n    *   Axes:\n        *   X-axis: t (no units given), Time\n        *   Y-axis:\n            *   Yo2 (%): Oxygen Concentration\n            *   PMX (%): Premix Fraction\n            *   TP(H2) (%): Total Thermal Power of Hydrogen\n            *   PRMS (-)/PRMS REF: Root Mean Square pressure\n    *   Curves:\n        * Plot A shows that Total Thermal Power of Hydrogen goes from 0 to 40 and back to 0.\n        * Plot B shows that Premix Fraction goes from 0 to 100 and back to 0.\n        * Plot C shows that oxygen level goes to 17 to 23 and back to 17.\n\n**3. Tables:**\n\nNO_VISUAL_CONTENT\n\n**4. Diagrams:**\n\nNO_VISUAL_CONTENT\n\n**5. Key Numbers, Constants, Parameters:**\n\n*   Premix fraction: 60% MAX for B5-CB case due to limits in upstream pressure.\n*   Premix fraction: 80% PMX, pressure oscillations increase sharply (baseline case w/ natural gas)\n*   Premix fraction: Shift to 90% with Hydrogen.", "chunk_type": "vision", "page": 7, "extraction": "gemini_flash_smart"}, {"chunk_id": "vision_all_gtp_25_1329_bd385e47_p0007", "paper_id": "gtp_25_1329_bd385e47", "title": "gtp-25-1329", "section": "Visual/Equation Content - Page 8", "text": "[VISUAL/EQUATION CONTENT - Page 8]\nHere's the breakdown of the technical content extracted from the provided text and image:\n\n**1. Mathematical Equations:**\n\nNO_VISUAL_CONTENT\n\n**2. Graphs/Charts:**\n\n*   **(a) CO at Yo2=16.6% and TP(H2)=5%**\n    *   Axes:\n        *   X-axis: PMX (%), Range: approximately 40 to 100\n        *   Y-axis: CO (ppm), Range: approximately 100 to 2500\n    *   Curves: B0, B1, B2, B4, B5-PMX, B5-CB, B6\n    *   Key Values: Data points depict correlations of CO (ppm) versus PMX (%) for various burner layouts.\n\n*   **(b) NOx at Yo2=16.6% and TP(H2)=5%**\n    *   Axes:\n        *   X-axis: PMX (%), Range: approximately 40 to 90\n        *   Y-axis: NOx (ppm), Range: approximately 0 to 10\n    *   Curves: B0, B1, B2, B4, B5-PMX, B5-CB, B6\n    *   Key Values: Data points depict correlations of NOx (ppm) versus PMX (%) for various burnerlayouts.\n\n**3. Tables:**\n\nNO_VISUAL_CONTENT\n\n**4. Diagrams:**\n\nNO_VISUAL_CONTENT\n\n**5. Key Numbers, Constants, Parameters:**\n\n*   Yo2 = 16.6% (Oxygen content)\n*   TP(H2) = 5% (Hydrogen content)\n*   50%PMX\n*   5% and 10% of total thermal power", "chunk_type": "vision", "page": 8, "extraction": "gemini_flash_smart"}, {"chunk_id": "vision_all_gtp_25_1329_bd385e47_p0008", "paper_id": "gtp_25_1329_bd385e47", "title": "gtp-25-1329", "section": "Visual/Equation Content - Page 9", "text": "[VISUAL/EQUATION CONTENT - Page 9]\nHere's a breakdown of the technical content extracted from the image:\n\n**1. Mathematical Equations:** NO_VISUAL_CONTENT\n\n**2. Graphs/Charts:**\n\n*   **Figure 10(a) CO at Y02 = 16.6% and 50%PMX:**\n    *   Axes:\n        *   y-axis: CO (ppm)\n        *   x-axis: B0, B1, B5-CB, B5-PMX\n    *   Curves: Two bar sets for each x-axis label:\n        *   TP(H2) = 5%\n        *   TP(H2) = 10%\n\n*   **Figure 10(b) NOx at Y02 = 16.6% and 50%PMX:**\n    *   Axes:\n        *   y-axis: NOx (ppm)\n        *   x-axis: B0, B1, B5-CB, B5-PMX\n    *   Curves: Two bar sets for each x-axis label:\n        *   TP(H2) = 5%\n        *   TP(H2) = 10%\n\n*   **Figure 11 Normalized OH* chemiluminescence images at 90%PMX and [TP(H2) = 10%] w/o EGR: comparison of B0 and B4**\n    *   Top row: B0, Bottom row: B4\n    *   Axes:\n        *   x-axis: x (mm)\n        *   y-axis: y (mm)\n        *   Color bar with OH(*) / OH(*)_MAX for heatmap (0 to 1)\n        *   x from 0 to 125\n        *   y from -50 to 50\n\n*   **Figure 11 Normalized OH* chemiluminescence images at 90%PMX and [TP(H2) = 10%] EGR: comparison of B0 and B4**\n    *   Top row: B0, Bottom row: B4\n    *   Axes:\n        *   x-axis: x (mm)\n        *   y-axis: y (mm)\n        *   Color bar with OH(*) / OH(*)_MAX for heatmap (0 to 1)\n        *   x from 0 to 125\n        *   y from -50 to 50\n\n*   **Figure 12(a) CO**\n    *   Axes:\n        *   y-axis: CO (ppm)\n        *   x-axis: Air, EGR\n    *   Curves: Two bar sets for each x-axis label:\n        *   B0\n        *   B4\n\n*   **Figure 12(b) NOx**\n    *   Axes:\n        *   y-axis: NOx (ppm)\n        *   x-axis: Air, EGR\n    *   Curves: Two bar sets for each x-axis label:\n        *   B0\n        *   B4\n\n**3. Tables:** NO_VISUAL_CONTENT\n\n**4. Diagrams:** NO_VISUAL_CONTENT\n\n**5. Key Numbers, Constants, Parameters:**\n\n*   Y02 = 16.6%\n*   50% PMX\n*   90% PMX\n*   TP(H2) = 5%\n*   TP(H2) = 10%", "chunk_type": "vision", "page": 9, "extraction": "gemini_flash_smart"}, {"chunk_id": "vision_all_gtp_25_1329_bd385e47_p0009", "paper_id": "gtp_25_1329_bd385e47", "title": "gtp-25-1329", "section": "Visual/Equation Content - Page 10", "text": "[VISUAL/EQUATION CONTENT - Page 10]\nHere's a breakdown of the technical content extracted from the provided text and image.\n\n**1. Mathematical Equations:**\n\nNO_VISUAL_CONTENT\n\n**2. Graphs/Charts:**\n\n*   **Axes:**\n    *   *X-axis*: -1 to 1 (no units specified)\n    *   *Y-axis:* (implied) represents normalized performance relative to a baseline.\n*   **Curves:** Not applicable, it can be identified as bar graph\n*   **Key values:** Values range from -1 to 1 showing performance of new combustor configurations relative to some baseline. Performance parameters assessed include:\n    *   LBO air\n    *   P\" NG air\n    *   P\" H2 air\n    *   NOx air\n    *   NOx EGR\n    *   CO air\n    *   CO EGR\n*   **Plots:**\n    *   (a) B1\n    *   (b) B2\n    *   (c) B4\n    *   (d) B5-CB\n    *   (e) B5-PMX\n    *   (f) B6\n\n**3. Tables:**\n\nNO_VISUAL_CONTENT\n\n**4. Diagrams:**\n\nThe image shows bar graphs, there is no diagrams.\n\n**5. Key numbers, constants, parameters:**\n\n*   100% H2 pilots", "chunk_type": "vision", "page": 10, "extraction": "gemini_flash_smart"}]