{
  "paper_id": "paper_4f642914_Fuel_effects_on_NOx_",
  "title": "Combustion and Flame 139 (2004) 90\u2013105",
  "authors": [
    "Sayangdev Naha",
    "Industrial Engineering",
    "Taylor Street"
  ],
  "year": 2004,
  "journal": null,
  "doi": null,
  "filename": "Fuel_effects_on_NOx_emissions_in_partially_premixed_flames.pdf",
  "credibility_score": 5,
  "topic_tags": [
    "NOx_emissions",
    "combustion_instability",
    "premixed",
    "premixer",
    "hydrogen",
    "gas_turbine",
    "spray",
    "LES"
  ],
  "abstract": "The requirement to signi\ufb01cantly reduce NOx and particulate emissions while maintaining combustor perfor-\nmance is one of the main drivers for internal combustion engine research. Partially premixing and using fuel blends\nrepresent two promising approaches for reducing both the NOx and the particulate emissions from \ufb02ames. This\npaper reports on the results of a numerical investigation on the effects of using different fuels on NOx emissions in\ncounter\ufb02ow partially premixed \ufb02ames. The fuels invest",
  "chunk_count": 23,
  "processed_at": "2026-04-03T06:55:57.936811",
  "checksum": "a9b92055016663b9e76ae5046f85bad5"
}